{"onboarding":{"$contentActions":[{"input":{"bypass":false,"$cardContent":{"document":{"id":"1ef12fe2-8e21-46ef-badd-82a4386944ed","type":"text/plain","content":"Entrada do usuário"},"editable":false,"deletable":false,"position":"right","editing":false},"$invalid":false},"$invalid":false}],"$conditionOutputs":[{"stateId":"f2dd582c-ef14-48a8-9f8e-aad0d38da1b0","conditions":[{"source":"input","comparison":"exists","values":[]}],"$id":"2d1ef1f9-fa48-4700-a8a7-e9a7d8793b25","$connId":"con_3","$invalid":false}],"$enteringCustomActions":[],"$leavingCustomActions":[],"$inputSuggestions":[],"$defaultOutput":{"stateId":"fallback","$invalid":false},"$tags":[],"id":"onboarding","root":true,"$title":"Início","$position":{"top":"120px","left":"644px"},"$invalidContentActions":false,"$invalidOutputs":false,"$invalidCustomActions":false,"$invalid":false},"fallback":{"$contentActions":[{"input":{"bypass":true,"$cardContent":{"document":{"id":"9c01d35f-b3e2-450a-b659-c160cd2b4160","type":"text/plain"},"editable":false,"deletable":true,"position":"right","editing":false},"$invalid":false},"$invalid":false}],"$conditionOutputs":[{"stateId":"error","conditions":[{"source":"input","comparison":"matches","values":[".*"]}],"$id":"8371049f-894a-4b8e-a97e-f6c110c004b6","$connId":"con_8","$invalid":false}],"$enteringCustomActions":[],"$leavingCustomActions":[],"$inputSuggestions":[],"$defaultOutput":{"stateId":"onboarding","$invalid":false},"$tags":[],"id":"fallback","$title":"Exceções","$position":{"top":"120px","left":"877px"},"$invalidContentActions":false,"$invalidOutputs":false,"$invalidCustomActions":false,"$invalid":false},"error":{"$contentActions":[{"action":{"$id":"37faa9d8-cfe6-4b77-bb89-7e0972efd6ce","type":"SendMessage","settings":{"id":"00000000-0000-0000-0000-000000000002","type":"application/vnd.lime.chatstate+json","content":{"state":"composing","interval":1000}},"$cardContent":{"document":{"id":"00000000-0000-0000-0000-000000000002","type":"application/vnd.lime.chatstate+json","content":{"state":"composing","interval":1000}},"editable":true,"deletable":true,"position":"left","editing":false}},"$invalid":false},{"action":{"$id":"83d99b1b-f142-40c2-accb-a444b6a5d216","type":"SendMessage","settings":{"id":"00000000-0000-0000-0000-000000000003","type":"text/plain","content":"Desculpe, não consegui entender!"},"$cardContent":{"document":{"id":"00000000-0000-0000-0000-000000000003","type":"text/plain","content":"Desculpe, não consegui entender!"},"editable":true,"deletable":true,"position":"left","editing":false}},"$invalid":false},{"input":{"bypass":true,"$cardContent":{"document":{"id":"5e5af9d2-0773-4888-b00a-f1c4d53d1dec","type":"text/plain"},"editable":false,"deletable":true,"position":"right","editing":false},"$invalid":false},"$invalid":false}],"$conditionOutputs":[],"$enteringCustomActions":[],"$leavingCustomActions":[],"$inputSuggestions":[],"$defaultOutput":{"stateId":"onboarding","$invalid":false},"$tags":[],"id":"error","$title":"Erro padrão","$position":{"top":"120px","left":"1488px"},"$invalidContentActions":false,"$invalidOutputs":false,"$invalidCustomActions":false,"$invalid":false},"f2dd582c-ef14-48a8-9f8e-aad0d38da1b0":{"$contentActions":[{"action":{"$id":"9ce6418c-4729-485b-bee5-8d4ca2aa97a5","type":"SendMessage","settings":{"id":"d63f5a79-9254-4691-a65f-916b94cd3957","type":"application/vnd.lime.chatstate+json","content":{"state":"composing","interval":1000}},"$cardContent":{"document":{"id":"d63f5a79-9254-4691-a65f-916b94cd3957","type":"application/vnd.lime.chatstate+json","content":{"state":"composing","interval":1000}},"editable":true,"deletable":true,"position":"left"}},"$invalid":false},{"action":{"$id":"db346374-8368-460b-aa43-ed5ba364f74a","type":"SendMessage","settings":{"id":"f21e4920-568a-4a6e-be53-91d8565f7b2c","type":"text/plain","content":"Olá, espero que esteja tudo.\nSou a Lora responsável por passar os valores da Take. ","metadata":{}},"$cardContent":{"document":{"id":"f21e4920-568a-4a6e-be53-91d8565f7b2c","type":"text/plain","content":"Olá, espero que esteja tudo.\nSou a Lora responsável por passar os valores da Take. "},"editable":true,"deletable":true,"position":"left"}},"$invalid":false},{"input":{"bypass":true,"$cardContent":{"document":{"id":"54909b1d-3e44-4232-a92d-78b8efe9e303","type":"text/plain","textContent":"Entrada do usuário","content":"Entrada do usuário"},"editable":false,"deletable":true,"position":"right","editing":false},"$invalid":false},"$invalid":false}],"$conditionOutputs":[{"stateId":"26b1126e-ec80-4c5e-875f-7315d5a76bca","$connId":"con_13","$id":"b8f59a8f-b543-44de-b85c-c18b5638e4d9","conditions":[{"source":"input","comparison":"exists","values":[]}],"$invalid":false}],"$enteringCustomActions":[],"$leavingCustomActions":[],"$inputSuggestions":[],"$defaultOutput":{"stateId":"fallback","$invalid":false},"$tags":[],"id":"f2dd582c-ef14-48a8-9f8e-aad0d38da1b0","root":false,"$title":"Saudação","$position":{"top":"252px","left":"644px"},"$invalidContentActions":false,"$invalidOutputs":false,"$invalidCustomActions":false,"$invalid":false},"26b1126e-ec80-4c5e-875f-7315d5a76bca":{"$contentActions":[{"input":{"bypass":true,"$cardContent":{"document":{"id":"99415047-0d86-43ee-818f-821c37df6c39","type":"text/plain","textContent":"Entrada do usuário","content":"Entrada do usuário"},"editable":false,"deletable":true,"position":"right","editing":false},"$invalid":false},"$invalid":false},{"action":{"$id":"1b9aa96b-7ac9-46f4-990f-7210561aa7c3","type":"SendMessage","settings":{"id":"9b9035b0-5c31-403a-99a5-e22db37c6fb7","type":"application/vnd.lime.chatstate+json","content":{"state":"composing","interval":1000},"metadata":{"#stateName":"{{state.name}}","#stateId":"{{state.id}}","#messageId":"{{input.message@id}}","#previousStateId":"{{state.previous.id}}","#previousStateName":"{{state.previous.name}}"}},"$cardContent":{"document":{"id":"9b9035b0-5c31-403a-99a5-e22db37c6fb7","type":"application/vnd.lime.chatstate+json","content":{"state":"composing","interval":1000}},"editable":true,"deletable":true,"position":"left"}},"$invalid":false},{"action":{"$id":"14cff5cb-fb8f-4020-9abf-6e25b7989542","type":"SendMessage","settings":{"id":"ccb3d882-ebfb-40c0-a20a-cb04ff962cda","type":"text/plain","content":"Mesmo eu sendo um robô e\nnão tendo consciência sobre o que é valores, posso te ajudar de alguma forma.","metadata":{"#stateName":"{{state.name}}","#stateId":"{{state.id}}","#messageId":"{{input.message@id}}","#previousStateId":"{{state.previous.id}}","#previousStateName":"{{state.previous.name}}"}},"$cardContent":{"document":{"id":"ccb3d882-ebfb-40c0-a20a-cb04ff962cda","type":"text/plain","content":"Mesmo eu sendo um robô e\nnão tendo consciência sobre o que é valores, posso te ajudar de alguma forma."},"editable":true,"deletable":true,"position":"left"}},"$invalid":false}],"$conditionOutputs":[{"stateId":"7fae7e22-8a3a-49d4-bf00-b0b4b0763d41","$connId":"con_18","$id":"d384b822-7b4f-468c-af88-d54d4d080059","conditions":[{"source":"input","comparison":"exists","values":[]}],"$invalid":false}],"$enteringCustomActions":[],"$leavingCustomActions":[],"$inputSuggestions":[],"$defaultOutput":{"stateId":"fallback","$invalid":false},"$tags":[],"id":"26b1126e-ec80-4c5e-875f-7315d5a76bca","root":false,"$title":"Eu robô","$position":{"top":"390px","left":"644px"},"$invalidContentActions":false,"$invalidOutputs":false,"$invalidCustomActions":false,"$invalid":false},"7fae7e22-8a3a-49d4-bf00-b0b4b0763d41":{"$contentActions":[{"action":{"$id":"4d29e409-da74-4b2a-b5cc-ff2d5d588b61","type":"SendMessage","settings":{"id":"ceb31160-d194-4132-a7a3-5e44d7a1bfc7","type":"application/vnd.lime.chatstate+json","content":{"state":"composing","interval":"4000"},"metadata":{"#stateName":"{{state.name}}","#stateId":"{{state.id}}","#messageId":"{{input.message@id}}","#previousStateId":"{{state.previous.id}}","#previousStateName":"{{state.previous.name}}"}},"$cardContent":{"document":{"id":"ceb31160-d194-4132-a7a3-5e44d7a1bfc7","type":"application/vnd.lime.chatstate+json","content":{"state":"composing","interval":"4000"}},"editable":true,"deletable":true,"position":"left"}},"$invalid":false},{"action":{"$id":"2fca1408-ccc0-4d02-ba04-8ab6ecb25fd9","type":"SendMessage","settings":{"id":"afc909cd-1158-4acb-9cab-6092fc857bb0","type":"text/plain","content":"Vamos lá...","metadata":{"#stateName":"{{state.name}}","#stateId":"{{state.id}}","#messageId":"{{input.message@id}}","#previousStateId":"{{state.previous.id}}","#previousStateName":"{{state.previous.name}}"}},"$cardContent":{"document":{"id":"afc909cd-1158-4acb-9cab-6092fc857bb0","type":"text/plain","content":"Vamos lá..."},"editable":true,"deletable":true,"position":"left"}},"$invalid":false},{"action":{"$id":"e4bc5112-034a-4815-b290-5b1319e27d45","type":"SendMessage","settings":{"id":"3d81c0e3-46ee-431f-a2c9-92028b4deff8","type":"application/vnd.lime.chatstate+json","content":{"state":"composing","interval":1000},"metadata":{"#stateName":"{{state.name}}","#stateId":"{{state.id}}","#messageId":"{{input.message@id}}","#previousStateId":"{{state.previous.id}}","#previousStateName":"{{state.previous.name}}"}},"$cardContent":{"document":{"id":"3d81c0e3-46ee-431f-a2c9-92028b4deff8","type":"application/vnd.lime.chatstate+json","content":{"state":"composing","interval":1000}},"editable":true,"deletable":true,"position":"left"}},"$invalid":false},{"action":{"$id":"5632865f-1d70-4ec8-bb6b-5727d44e300b","type":"SendMessage","settings":{"id":"d3cb40fb-d2d6-4aa0-9775-6d46be2f8516","type":"text/plain","content":"A cultura Take tem como base 6 valores que são:","metadata":{"#stateName":"{{state.name}}","#stateId":"{{state.id}}","#messageId":"{{input.message@id}}","#previousStateId":"{{state.previous.id}}","#previousStateName":"{{state.previous.name}}"}},"$cardContent":{"document":{"id":"d3cb40fb-d2d6-4aa0-9775-6d46be2f8516","type":"text/plain","content":"A cultura Take tem como base 6 valores que são:"},"editable":true,"deletable":true,"position":"left"}},"$invalid":false},{"action":{"$id":"0c63437f-6c43-4bac-9e7b-6aa134714d60","type":"SendMessage","settings":{"id":"22ad0b45-ce62-442b-a41b-b29964b68b99","type":"application/vnd.lime.chatstate+json","content":{"state":"composing","interval":1000},"metadata":{"#stateName":"{{state.name}}","#stateId":"{{state.id}}","#messageId":"{{input.message@id}}","#previousStateId":"{{state.previous.id}}","#previousStateName":"{{state.previous.name}}"}},"$cardContent":{"document":{"id":"22ad0b45-ce62-442b-a41b-b29964b68b99","type":"application/vnd.lime.chatstate+json","content":{"state":"composing","interval":1000}},"editable":true,"deletable":true,"position":"left"}},"$invalid":false},{"action":{"$id":"1021157d-d13e-480e-a730-40af15e08b3a","type":"SendMessage","settings":{"id":"a1489ca5-f966-43c5-979c-b618fc627ec7","type":"application/vnd.lime.collection+json","content":{"itemType":"application/vnd.lime.document-select+json","items":[{"header":{"type":"application/vnd.lime.media-link+json","value":{"title":"Take.Be","text":"Pessoas em 1º lugar","type":"image/png","uri":"https://user-images.githubusercontent.com/67064886/126578036-6ada91dd-dd48-43f8-a740-69e7c2479174.png","aspectRatio":"2:1"}},"options":[{"label":{"type":"text/plain","value":"💙 Saber mais"},"value":null}],"id":0,"editing":false},{"header":{"type":"application/vnd.lime.media-link+json","value":{"title":"Take.Team","text":"Em nosso time, cada pessoa dá o seu melhor","type":"image/png","uri":"https://user-images.githubusercontent.com/67064886/126578041-b2416b5a-506d-40b3-9a7c-07f168551ce2.png","aspectRatio":"2:1"}},"options":[{"label":{"type":"text/plain","value":"🏳️ Saber mais"},"value":null}],"id":1,"editing":false},{"header":{"type":"application/vnd.lime.media-link+json","value":{"title":"Take.Execellence","text":"Excelente é o nosso ponto de partida","type":"image/png","uri":"https://user-images.githubusercontent.com/67064886/126578037-a74fc959-41f0-4e1f-a0aa-75c00cd04c19.png","aspectRatio":"2:1"}},"options":[{"label":{"type":"text/plain","value":"⭐ Saber mais"},"value":null}],"editing":false,"id":2},{"header":{"type":"application/vnd.lime.media-link+json","value":{"title":"Take.Charge","text":"Apropriar-se para fazer a diferença","type":"image/png","uri":"https://user-images.githubusercontent.com/67064886/126578040-dcc89b7f-97bf-4028-8bb4-89174e3c2140.png","aspectRatio":"2:1"}},"options":[{"label":{"type":"text/plain","value":"⚡ Saber mais"},"value":null}],"editing":false,"id":3},{"header":{"type":"application/vnd.lime.media-link+json","value":{"title":"Take.Simple","text":"Simplicidade é o último grau de sofisticação","type":"image/png","uri":"https://user-images.githubusercontent.com/67064886/126581844-2a17367d-c34b-4632-900f-7490d68541c2.png","aspectRatio":"2:1"}},"options":[{"label":{"type":"text/plain","value":"🎯 Saber mais"},"value":null}],"editing":false,"id":4},{"header":{"type":"application/vnd.lime.media-link+json","value":{"title":"Take.Higher","text":"Pensar grande e ir além","type":"image/png","uri":"https://user-images.githubusercontent.com/67064886/126578038-679a9eb6-5433-4e7e-84b0-b077499015cb.png","aspectRatio":"2:1"}},"options":[{"label":{"type":"text/plain","value":"Fazer desafio"},"value":null},{"label":{"type":"text/plain","value":"🚀 Saber mais"},"value":null}],"editing":false,"id":5},{"header":{"type":"application/vnd.lime.media-link+json","value":{"title":"Desafio","text":"----","type":"image/png","uri":"https://user-images.githubusercontent.com/67064886/126578033-826b786d-2832-454f-a9fc-12182725f0cd.png","aspectRatio":"2:1"}},"options":[{"label":{"type":"text/plain","value":"Fazer desafio"},"value":null}],"editing":false,"id":6}]},"metadata":{"#stateName":"{{state.name}}","#stateId":"{{state.id}}","#messageId":"{{input.message@id}}","#previousStateId":"{{state.previous.id}}","#previousStateName":"{{state.previous.name}}"}},"$cardContent":{"document":{"id":"a1489ca5-f966-43c5-979c-b618fc627ec7","type":"application/vnd.lime.collection+json","content":{"itemType":"application/vnd.lime.document-select+json","items":[{"header":{"type":"application/vnd.lime.media-link+json","value":{"title":"Take.Be","text":"Pessoas em 1º lugar","type":"image/png","uri":"https://user-images.githubusercontent.com/67064886/126578036-6ada91dd-dd48-43f8-a740-69e7c2479174.png","aspectRatio":"2:1"}},"options":[{"label":{"type":"text/plain","value":"💙 Saber mais"},"value":null}],"id":0,"editing":false},{"header":{"type":"application/vnd.lime.media-link+json","value":{"title":"Take.Team","text":"Em nosso time, cada pessoa dá o seu melhor","type":"image/png","uri":"https://user-images.githubusercontent.com/67064886/126578041-b2416b5a-506d-40b3-9a7c-07f168551ce2.png","aspectRatio":"2:1"}},"options":[{"label":{"type":"text/plain","value":"🏳️ Saber mais"},"value":null}],"id":1,"editing":false},{"header":{"type":"application/vnd.lime.media-link+json","value":{"title":"Take.Execellence","text":"Excelente é o nosso ponto de partida","type":"image/png","uri":"https://user-images.githubusercontent.com/67064886/126578037-a74fc959-41f0-4e1f-a0aa-75c00cd04c19.png","aspectRatio":"2:1"}},"options":[{"label":{"type":"text/plain","value":"⭐ Saber mais"},"value":null}],"editing":false,"id":2},{"header":{"type":"application/vnd.lime.media-link+json","value":{"title":"Take.Charge","text":"Apropriar-se para fazer a diferença","type":"image/png","uri":"https://user-images.githubusercontent.com/67064886/126578040-dcc89b7f-97bf-4028-8bb4-89174e3c2140.png","aspectRatio":"2:1"}},"options":[{"label":{"type":"text/plain","value":"⚡ Saber mais"},"value":null}],"editing":false,"id":3},{"header":{"type":"application/vnd.lime.media-link+json","value":{"title":"Take.Simple","text":"Simplicidade é o último grau de sofisticação","type":"image/png","uri":"https://user-images.githubusercontent.com/67064886/126581844-2a17367d-c34b-4632-900f-7490d68541c2.png","aspectRatio":"2:1"}},"options":[{"label":{"type":"text/plain","value":"🎯 Saber mais"},"value":null}],"editing":false,"id":4},{"header":{"type":"application/vnd.lime.media-link+json","value":{"title":"Take.Higher","text":"Pensar grande e ir além","type":"image/png","uri":"https://user-images.githubusercontent.com/67064886/126578038-679a9eb6-5433-4e7e-84b0-b077499015cb.png","aspectRatio":"2:1"}},"options":[{"label":{"type":"text/plain","value":"Fazer desafio"},"value":null},{"label":{"type":"text/plain","value":"🚀 Saber mais"},"value":null}],"editing":false,"id":5},{"header":{"type":"application/vnd.lime.media-link+json","value":{"title":"Desafio","text":"----","type":"image/png","uri":"https://user-images.githubusercontent.com/67064886/126578033-826b786d-2832-454f-a9fc-12182725f0cd.png","aspectRatio":"2:1"}},"options":[{"label":{"type":"text/plain","value":"Fazer desafio"},"value":null}],"editing":false,"id":6}]}},"editable":true,"deletable":true,"position":"left"}},"$invalid":false},{"input":{"bypass":false,"$cardContent":{"document":{"id":"ae10995d-6fba-427b-b412-7f6b0eabb830","type":"text/plain","textContent":"Entrada do usuário","content":"Entrada do usuário"},"editable":false,"deletable":true,"position":"right","editing":false},"$invalid":false},"$invalid":false}],"$conditionOutputs":[{"stateId":"a8260378-4ea1-4522-99c5-f468570700f8","$connId":"con_23","$id":"0b6fdf81-e68c-4f35-9463-b1abb9cfd76b","conditions":[{"source":"input","comparison":"equals","values":["💙 Saber mais"]}],"$invalid":false},{"$id":"171480d4-bc55-47e2-9ee7-9be9909fd472","conditions":[{"source":"input","comparison":"equals","values":["🏳️ Saber mais"]}],"$invalid":false,"stateId":"c16b004e-1727-474c-a294-cfeeb6eec153","$connId":"con_28"},{"stateId":"18be2a78-0a71-4c94-83a5-e77e818d84ce","$connId":"con_33","$id":"45829d4f-69cb-4a3d-bbb8-f1a4f8de1582","conditions":[{"source":"input","comparison":"equals","values":["⭐ Saber mais"]}],"$invalid":false},{"stateId":"ab10bb75-e167-4f6f-8be1-a9aed05a6b3f","$connId":"con_38","$id":"b3ebb451-88a4-4f60-b46b-cf2acbb0bf70","conditions":[{"source":"input","comparison":"equals","values":["⚡ Saber mais"]}],"$invalid":false},{"stateId":"c7d51507-e323-4722-ac59-42f0747e5a18","$connId":"con_43","$id":"d9a3af05-b72f-4f61-a52b-7eeece3c3b03","conditions":[{"source":"input","comparison":"equals","values":["🎯 Saber mais"]}],"$invalid":false},{"stateId":"c7d51507-e323-4722-ac59-42f0747e5a18","$connId":"con_48","$id":"2c714959-6caf-4d22-aff9-4d320b3f8ab8","conditions":[{"source":"input","comparison":"equals","values":["🚀 Saber mais"]}],"$invalid":false},{"stateId":"e99c3d4f-3960-4a87-ad59-11a76626327a","$connId":"con_53","$id":"4d8f9fa0-5db0-4568-a9ef-52502d3dc8fd","conditions":[{"source":"input","comparison":"equals","values":["Fazer desafio"]}],"$invalid":false}],"$enteringCustomActions":[],"$leavingCustomActions":[],"$inputSuggestions":["First option","Second option"],"$defaultOutput":{"stateId":"fallback","$invalid":false},"$tags":[],"id":"7fae7e22-8a3a-49d4-bf00-b0b4b0763d41","root":false,"$title":"Carrosel","$position":{"top":"538px","left":"644px"},"$invalidContentActions":false,"$invalidOutputs":false,"$invalidCustomActions":false,"$invalid":false},"a8260378-4ea1-4522-99c5-f468570700f8":{"$contentActions":[{"action":{"$id":"b088c4ad-c9cb-459c-91ed-3510ea9cd3c6","type":"SendMessage","settings":{"id":"2d988180-7f0f-4f26-925c-54b028e222d1","type":"application/vnd.lime.chatstate+json","content":{"state":"composing","interval":1000}},"$cardContent":{"document":{"id":"2d988180-7f0f-4f26-925c-54b028e222d1","type":"application/vnd.lime.chatstate+json","content":{"state":"composing","interval":1000}},"editable":true,"deletable":true,"position":"left"}},"$invalid":false},{"action":{"$id":"8dd543c7-fd93-41d5-b6c7-800bd9bb4c9e","type":"SendMessage","settings":{"id":"05d47357-9d60-47d1-9f71-a4f5a245952e","type":"text/plain","content":"A Take é feita por pessoas e para pessoas. Nossas relações são transparentes e humanizadas.","metadata":{}},"$cardContent":{"document":{"id":"05d47357-9d60-47d1-9f71-a4f5a245952e","type":"text/plain","content":"A Take é feita por pessoas e para pessoas. Nossas relações são transparentes e humanizadas."},"editable":true,"deletable":true,"position":"left"}},"$invalid":false},{"action":{"$id":"4450e2cc-fff9-454d-b66c-b4da10a6bc22","type":"SendMessage","settings":{"id":"33c01a05-8a1a-4fba-9024-7479bb003331","type":"application/vnd.lime.chatstate+json","content":{"state":"composing","interval":1000}},"$cardContent":{"document":{"id":"33c01a05-8a1a-4fba-9024-7479bb003331","type":"application/vnd.lime.chatstate+json","content":{"state":"composing","interval":1000}},"editable":true,"deletable":true,"position":"left"}},"$invalid":false},{"action":{"$id":"ad258c60-19c6-4447-a81c-7a64949f783e","type":"SendMessage","settings":{"id":"2f08e677-d3f6-4ace-ae8d-ae353a1351ce","type":"text/plain","content":" Cada cliente, cada parceiro e cada Take.Ser é valorizado e respeitado em sua individualidade e está presente em cada bit de nossa empresa.","metadata":{}},"$cardContent":{"document":{"id":"2f08e677-d3f6-4ace-ae8d-ae353a1351ce","type":"text/plain","content":" Cada cliente, cada parceiro e cada Take.Ser é valorizado e respeitado em sua individualidade e está presente em cada bit de nossa empresa."},"editable":true,"deletable":true,"position":"left"}},"$invalid":false},{"input":{"bypass":true,"$cardContent":{"document":{"id":"f1e4d371-e88d-4007-a589-6d8ca5815466","type":"text/plain","textContent":"Entrada do usuário","content":"Entrada do usuário"},"editable":false,"deletable":true,"position":"right","editing":false},"$invalid":false},"$invalid":false}],"$conditionOutputs":[{"stateId":"f6df1391-b0ed-423c-be6c-8ac2be25f321","$connId":"con_58","$id":"30f0148b-ce7d-4be1-8642-ac344f001b5a","conditions":[{"source":"input","comparison":"exists","values":[]}],"$invalid":false}],"$enteringCustomActions":[],"$leavingCustomActions":[],"$inputSuggestions":[],"$defaultOutput":{"stateId":"fallback","$invalid":false},"$tags":[],"id":"a8260378-4ea1-4522-99c5-f468570700f8","root":false,"$title":"Take.Be","$position":{"top":"707px","left":"644px"},"$invalidContentActions":false,"$invalidOutputs":false,"$invalidCustomActions":false,"$invalid":false},"c16b004e-1727-474c-a294-cfeeb6eec153":{"$contentActions":[{"action":{"$id":"65e75509-28cc-4687-9415-951fdd4632d4","type":"SendMessage","settings":{"id":"b402fad3-d96d-443d-8293-26d402709b74","type":"application/vnd.lime.chatstate+json","content":{"state":"composing","interval":1000}},"$cardContent":{"document":{"id":"b402fad3-d96d-443d-8293-26d402709b74","type":"application/vnd.lime.chatstate+json","content":{"state":"composing","interval":1000}},"editable":true,"deletable":true,"position":"left"}},"$invalid":false},{"action":{"$id":"5045f269-b183-4608-a603-678dd0261160","type":"SendMessage","settings":{"id":"5c39bf02-60ed-499f-9de3-aaf060199e15","type":"text/plain","content":"Sabemos que o que faz uma equipe incrível são pessoas incríveis em cooperação. Assim, cada Take.ser busca cumprir sua parte para garantir a vitória do time.","metadata":{}},"$cardContent":{"document":{"id":"5c39bf02-60ed-499f-9de3-aaf060199e15","type":"text/plain","content":"Sabemos que o que faz uma equipe incrível são pessoas incríveis em cooperação. Assim, cada Take.ser busca cumprir sua parte para garantir a vitória do time."},"editable":true,"deletable":true,"position":"left"}},"$invalid":false},{"input":{"bypass":true,"$cardContent":{"document":{"id":"8278eebd-87a3-4040-8c55-300cb2b424a9","type":"text/plain","textContent":"Entrada do usuário","content":"Entrada do usuário"},"editable":false,"deletable":true,"position":"right","editing":false},"$invalid":false},"$invalid":false}],"$conditionOutputs":[{"stateId":"f6df1391-b0ed-423c-be6c-8ac2be25f321","$connId":"con_63","$id":"a2e1b068-a2df-4d61-8409-e31c4b5a8de8","conditions":[{"source":"input","comparison":"exists","values":[]}],"$invalid":false}],"$enteringCustomActions":[],"$leavingCustomActions":[],"$inputSuggestions":[],"$defaultOutput":{"stateId":"fallback","$invalid":false},"$tags":[],"id":"c16b004e-1727-474c-a294-cfeeb6eec153","root":false,"$title":"Take.Team","$position":{"top":"708px","left":"844px"},"$invalidContentActions":false,"$invalidOutputs":false,"$invalidCustomActions":false,"$invalid":false},"18be2a78-0a71-4c94-83a5-e77e818d84ce":{"$contentActions":[{"action":{"$id":"6a535c5f-84b2-4e96-8d09-45676cffc9ba","type":"SendMessage","settings":{"id":"b2edff4d-4741-4eb8-b168-d45ff0b161e5","type":"application/vnd.lime.chatstate+json","content":{"state":"composing","interval":1000}},"$cardContent":{"document":{"id":"b2edff4d-4741-4eb8-b168-d45ff0b161e5","type":"application/vnd.lime.chatstate+json","content":{"state":"composing","interval":1000}},"editable":true,"deletable":true,"position":"left"}},"$invalid":false},{"action":{"$id":"37532b3b-9821-466a-9c74-2eeeb6d6203a","type":"SendMessage","settings":{"id":"a1998518-b485-4c87-9dff-43e1a6824caa","type":"text/plain","content":"Com nosso espírito geek e nossa disposição para aprender e crescer, buscamos estar sempre um passo a frente e superarmos os mais exigentes padrões.","metadata":{}},"$cardContent":{"document":{"id":"a1998518-b485-4c87-9dff-43e1a6824caa","type":"text/plain","content":"Com nosso espírito geek e nossa disposição para aprender e crescer, buscamos estar sempre um passo a frente e superarmos os mais exigentes padrões."},"editable":true,"deletable":true,"position":"left"}},"$invalid":false},{"input":{"bypass":true,"$cardContent":{"document":{"id":"09dade6a-12ef-4c1e-a744-b65a3a7e750d","type":"text/plain","textContent":"Entrada do usuário","content":"Entrada do usuário"},"editable":false,"deletable":true,"position":"right","editing":false},"$invalid":false},"$invalid":false}],"$conditionOutputs":[{"stateId":"f6df1391-b0ed-423c-be6c-8ac2be25f321","$connId":"con_68","$id":"11e44f78-4da6-41a9-b84e-4a3676cef7ad","conditions":[{"source":"input","comparison":"exists","values":[]}],"$invalid":false}],"$enteringCustomActions":[],"$leavingCustomActions":[],"$inputSuggestions":[],"$defaultOutput":{"stateId":"fallback","$invalid":false},"$tags":[],"id":"18be2a78-0a71-4c94-83a5-e77e818d84ce","root":false,"$title":"Take.Execellence","$position":{"top":"711px","left":"1043px"},"$invalidContentActions":false,"$invalidOutputs":false,"$invalidCustomActions":false,"$invalid":false},"ab10bb75-e167-4f6f-8be1-a9aed05a6b3f":{"$contentActions":[{"action":{"$id":"c350e502-2917-4ac7-a4ac-3f7445b8f83b","type":"SendMessage","settings":{"id":"d285a3db-c20d-45c9-9068-63acad3d5218","type":"application/vnd.lime.chatstate+json","content":{"state":"composing","interval":1000}},"$cardContent":{"document":{"id":"d285a3db-c20d-45c9-9068-63acad3d5218","type":"application/vnd.lime.chatstate+json","content":{"state":"composing","interval":1000}},"editable":true,"deletable":true,"position":"left"}},"$invalid":false},{"action":{"$id":"f0f26101-63fd-4b9a-ac3b-8b4bc4f6ec80","type":"SendMessage","settings":{"id":"be4fb5ac-822d-4376-9fd0-3f1f295c3e42","type":"text/plain","content":"Apostamos em profissionais que chamam a responsabilidade para si e que, sem medo de ousar, transformem o mundo a sua volta, com muita competência e criatividade!","metadata":{}},"$cardContent":{"document":{"id":"be4fb5ac-822d-4376-9fd0-3f1f295c3e42","type":"text/plain","content":"Apostamos em profissionais que chamam a responsabilidade para si e que, sem medo de ousar, transformem o mundo a sua volta, com muita competência e criatividade!"},"editable":true,"deletable":true,"position":"left"}},"$invalid":false},{"input":{"bypass":true,"$cardContent":{"document":{"id":"c19cc302-32c6-47e2-bfaf-a0b1beb2c659","type":"text/plain","textContent":"Entrada do usuário","content":"Entrada do usuário"},"editable":false,"deletable":true,"position":"right","editing":false},"$invalid":false},"$invalid":false}],"$conditionOutputs":[{"stateId":"f6df1391-b0ed-423c-be6c-8ac2be25f321","$connId":"con_73","$id":"c6ef4f07-3bde-48e4-88ef-ec903091226c","conditions":[{"source":"input","comparison":"exists","values":[]}],"$invalid":false}],"$enteringCustomActions":[],"$leavingCustomActions":[],"$inputSuggestions":[],"$defaultOutput":{"stateId":"fallback","$invalid":false},"$tags":[],"id":"ab10bb75-e167-4f6f-8be1-a9aed05a6b3f","root":false,"$title":"Take.Charge","$position":{"top":"711px","left":"1243px"},"$invalidContentActions":false,"$invalidOutputs":false,"$invalidCustomActions":false,"$invalid":false},"c7d51507-e323-4722-ac59-42f0747e5a18":{"$contentActions":[{"action":{"$id":"0af68dfb-cb4e-4d4e-9895-4497c7639932","type":"SendMessage","settings":{"id":"e8401379-e07e-4bd6-93f6-ef32fcb4603f","type":"application/vnd.lime.chatstate+json","content":{"state":"composing","interval":1000}},"$cardContent":{"document":{"id":"e8401379-e07e-4bd6-93f6-ef32fcb4603f","type":"application/vnd.lime.chatstate+json","content":{"state":"composing","interval":1000}},"editable":true,"deletable":true,"position":"left"}},"$invalid":false},{"action":{"$id":"9f3fe7d3-ba50-414a-836f-298d5325921c","type":"SendMessage","settings":{"id":"f29a1f10-3c57-4682-b19e-5ad6a0740b4c","type":"text/plain","content":"Mantemos o foco no essencial. Menos é mais.","metadata":{}},"$cardContent":{"document":{"id":"f29a1f10-3c57-4682-b19e-5ad6a0740b4c","type":"text/plain","content":"Mantemos o foco no essencial. Menos é mais."},"editable":true,"deletable":true,"position":"left"}},"$invalid":false},{"input":{"bypass":true,"$cardContent":{"document":{"id":"c6916d22-1869-4768-bfed-fffe3090b97e","type":"text/plain","textContent":"Entrada do usuário","content":"Entrada do usuário"},"editable":false,"deletable":true,"position":"right","editing":false},"$invalid":false},"$invalid":false}],"$conditionOutputs":[{"stateId":"f6df1391-b0ed-423c-be6c-8ac2be25f321","$connId":"con_78","$id":"e3591782-0bf1-46ff-96e7-9018630f223a","conditions":[{"source":"input","comparison":"exists","values":[]}],"$invalid":false}],"$enteringCustomActions":[],"$leavingCustomActions":[],"$inputSuggestions":[],"$defaultOutput":{"stateId":"fallback","$invalid":false},"$tags":[],"id":"c7d51507-e323-4722-ac59-42f0747e5a18","root":false,"$title":"Take.Simple","$position":{"top":"710px","left":"1445px"},"$invalidContentActions":false,"$invalidOutputs":false,"$invalidCustomActions":false,"$invalid":false},"e99c3d4f-3960-4a87-ad59-11a76626327a":{"$contentActions":[{"action":{"$id":"6d32b592-7e8b-4683-b64a-ef0980a60f2c","type":"SendMessage","settings":{"id":"a46504ce-69b6-4329-930d-d3cd58fc25d7","type":"application/vnd.lime.chatstate+json","content":{"state":"composing","interval":1000}},"$cardContent":{"document":{"id":"a46504ce-69b6-4329-930d-d3cd58fc25d7","type":"application/vnd.lime.chatstate+json","content":{"state":"composing","interval":1000}},"editable":true,"deletable":true,"position":"left"}},"$invalid":false},{"action":{"$id":"07780b49-012f-4058-8c8e-4b7c8ff2ebd6","type":"SendMessage","settings":{"id":"2b85c3e4-1d35-45b0-9b3c-7a4c9074db9a","type":"text/plain","content":"Conforme solicitado no e-mail\nenviado, o resultado do desafio\nestá disponível abaixo...","metadata":{}},"$cardContent":{"document":{"id":"2b85c3e4-1d35-45b0-9b3c-7a4c9074db9a","type":"text/plain","content":"Conforme solicitado no e-mail\nenviado, o resultado do desafio\nestá disponível abaixo..."},"editable":true,"deletable":true,"position":"left"}},"$invalid":false},{"input":{"bypass":true,"$cardContent":{"document":{"id":"0fb77aab-43cb-4a27-8e91-a55e40029178","type":"text/plain","textContent":"Entrada do usuário","content":"Entrada do usuário"},"editable":false,"deletable":true,"position":"right","editing":false},"$invalid":false},"$invalid":false}],"$conditionOutputs":[{"stateId":"eb45fcef-9f9a-4395-ad28-b21494eea486","$connId":"con_83","$id":"a78518f1-9185-46c9-98bb-6bb7cb05d360","conditions":[{"source":"input","comparison":"exists","values":[]}],"$invalid":false}],"$enteringCustomActions":[],"$leavingCustomActions":[],"$inputSuggestions":[],"$defaultOutput":{"stateId":"fallback","$invalid":false},"$tags":[],"id":"e99c3d4f-3960-4a87-ad59-11a76626327a","root":false,"$title":"Desafio","$position":{"top":"713px","left":"1916px"},"$invalidContentActions":false,"$invalidOutputs":false,"$invalidCustomActions":false,"$invalid":false},"f6df1391-b0ed-423c-be6c-8ac2be25f321":{"$contentActions":[{"action":{"$id":"d23dee1c-b1a4-4c0b-8c4c-fe61e9c1e29f","type":"SendMessage","settings":{"id":"75b48e38-e6f5-4987-b5cf-c9cfa2e46d2d","type":"application/vnd.lime.chatstate+json","content":{"state":"composing","interval":1000}},"$cardContent":{"document":{"id":"75b48e38-e6f5-4987-b5cf-c9cfa2e46d2d","type":"application/vnd.lime.chatstate+json","content":{"state":"composing","interval":1000}},"editable":true,"deletable":true,"position":"left"}},"$invalid":false},{"action":{"$id":"8a4f7c79-95e2-4d4a-ba46-13d5b9627973","type":"SendMessage","settings":{"id":"334a3a80-3a23-4f9e-84d3-dd942ac82817","type":"application/vnd.lime.select+json","content":{"text":"Se quiser saber mais sobre outros valores é só falar","scope":"immediate","options":[{"text":"💙 Be","previewText":"💙 Be","value":null,"index":0,"type":null},{"text":"🏳️ Team","previewText":"🏳️ Team","value":null,"index":1,"type":null},{"index":-1,"text":"⭐ Excellence","previewText":"⭐ Excellence","type":null,"value":null},{"index":-1,"text":"⚡ Charge","previewText":"⚡ Charge","type":null,"value":null},{"index":-1,"text":"🎯 Simple","previewText":"🎯 Simple","type":null,"value":null},{"index":-1,"text":"🚀 Higher","previewText":"🚀 Higher","type":null,"value":null},{"index":-1,"text":"💡 Desafio","previewText":"💡 Desafio","type":null,"value":null}]},"metadata":{}},"$cardContent":{"document":{"id":"334a3a80-3a23-4f9e-84d3-dd942ac82817","type":"application/vnd.lime.select+json","content":{"text":"Se quiser saber mais sobre outros valores é só falar","scope":"immediate","options":[{"text":"💙 Be","previewText":"💙 Be","value":null,"index":0,"type":null},{"text":"🏳️ Team","previewText":"🏳️ Team","value":null,"index":1,"type":null},{"index":-1,"text":"⭐ Excellence","previewText":"⭐ Excellence","type":null,"value":null},{"index":-1,"text":"⚡ Charge","previewText":"⚡ Charge","type":null,"value":null},{"index":-1,"text":"🎯 Simple","previewText":"🎯 Simple","type":null,"value":null},{"index":-1,"text":"🚀 Higher","previewText":"🚀 Higher","type":null,"value":null},{"index":-1,"text":"💡 Desafio","previewText":"💡 Desafio","type":null,"value":null}]}},"editable":true,"deletable":true,"position":"left"}},"$invalid":false},{"input":{"bypass":false,"$cardContent":{"document":{"id":"7954c6e3-4316-493d-93f8-eab1c7f8e6f8","type":"text/plain","textContent":"Entrada do usuário","content":"Entrada do usuário"},"editable":false,"deletable":true,"position":"right","editing":false},"$invalid":false},"$invalid":false}],"$conditionOutputs":[{"stateId":"a8260378-4ea1-4522-99c5-f468570700f8","$connId":"con_88","$id":"522d61f5-68da-4f4f-b747-47a728a21dec","conditions":[{"source":"input","comparison":"equals","values":["💙 Be"]}],"$invalid":false},{"stateId":"c16b004e-1727-474c-a294-cfeeb6eec153","$connId":"con_93","$id":"5c06fba8-4b5b-431a-a8b2-c39e0074d698","conditions":[{"source":"input","comparison":"equals","values":["🏳️ Team"]}],"$invalid":false},{"stateId":"18be2a78-0a71-4c94-83a5-e77e818d84ce","$connId":"con_98","$id":"190fe52f-f6b1-47fc-8280-0c7226f6f813","conditions":[{"source":"input","comparison":"equals","values":["⭐ Excellence"]}],"$invalid":false},{"stateId":"c7d51507-e323-4722-ac59-42f0747e5a18","$connId":"con_103","$id":"af16d63d-f56c-4230-83a9-7a230c2ceade","conditions":[{"source":"input","comparison":"equals","values":["🎯 Simple"]}],"$invalid":false},{"stateId":"ab10bb75-e167-4f6f-8be1-a9aed05a6b3f","$connId":"con_108","$id":"a4635b58-1fc1-4c51-a280-8b581004aefd","conditions":[{"source":"input","comparison":"equals","values":["⚡ Charge"]}],"$invalid":false},{"stateId":"c1f42350-80bf-42d5-aa6b-b868b1dd22f4","$connId":"con_113","$id":"decf8585-8dc1-437c-a2a5-7cab0ab9122d","conditions":[{"source":"input","comparison":"equals","values":["🚀 Higher"]}],"$invalid":false},{"stateId":"e99c3d4f-3960-4a87-ad59-11a76626327a","$connId":"con_118","$id":"33bfc1c8-cd36-4de6-a8ef-0e6475ac6c1a","conditions":[{"source":"input","comparison":"equals","values":["💡 Desafio"]}],"$invalid":false}],"$enteringCustomActions":[],"$leavingCustomActions":[],"$inputSuggestions":["💙 Be","🏳️ Team","⭐ Excellence","⚡ Charge","🎯 Simple","🚀 Higher","💡 Desafio"],"$defaultOutput":{"stateId":"fallback","$invalid":false},"$tags":[],"id":"f6df1391-b0ed-423c-be6c-8ac2be25f321","root":false,"$title":"Opções","$position":{"top":"918px","left":"1348px"},"$invalidContentActions":false,"$invalidOutputs":false,"$invalidCustomActions":false,"$invalid":false},"c1f42350-80bf-42d5-aa6b-b868b1dd22f4":{"$contentActions":[{"action":{"$id":"5306a3c1-e152-47bf-9a3f-ad72dd1a06d3","type":"SendMessage","settings":{"id":"7aedaf91-d69a-47db-a8da-4052f3a63c20","type":"application/vnd.lime.chatstate+json","content":{"state":"composing","interval":1000}},"$cardContent":{"document":{"id":"7aedaf91-d69a-47db-a8da-4052f3a63c20","type":"application/vnd.lime.chatstate+json","content":{"state":"composing","interval":1000}},"editable":true,"deletable":true,"position":"left"}},"$invalid":false},{"action":{"$id":"a14aa85f-627d-427e-80bd-1beb2fccf8d0","type":"SendMessage","settings":{"id":"2d2b6f9e-0ea9-4d96-9674-b1ea494ddea7","type":"text/plain","content":"Não temos medo de sonhar grande, pois sabemos que temos talento e determinação para realizar coisas incríveis!","metadata":{}},"$cardContent":{"document":{"id":"2d2b6f9e-0ea9-4d96-9674-b1ea494ddea7","type":"text/plain","content":"Não temos medo de sonhar grande, pois sabemos que temos talento e determinação para realizar coisas incríveis!"},"editable":true,"deletable":true,"position":"left"}},"$invalid":false},{"input":{"bypass":true,"$cardContent":{"document":{"id":"464c3dda-8a88-4f11-ad07-53d09a7c2241","type":"text/plain","textContent":"Entrada do usuário","content":"Entrada do usuário"},"editable":false,"deletable":true,"position":"right","editing":false},"$invalid":false},"$invalid":false}],"$conditionOutputs":[{"stateId":"f6df1391-b0ed-423c-be6c-8ac2be25f321","$connId":"con_123","$id":"aca1169b-9bcf-4ebc-9994-4ab9c901c9f6","conditions":[{"source":"input","comparison":"exists","values":[]}],"$invalid":false}],"$enteringCustomActions":[],"$leavingCustomActions":[],"$inputSuggestions":[],"$defaultOutput":{"stateId":"fallback","$invalid":false},"$tags":[],"id":"c1f42350-80bf-42d5-aa6b-b868b1dd22f4","root":false,"$title":"Take.Higher","$position":{"top":"711px","left":"1647px"},"$invalidContentActions":false,"$invalidOutputs":false,"$invalidCustomActions":false,"$invalid":false},"eb45fcef-9f9a-4395-ad28-b21494eea486":{"$contentActions":[{"action":{"$id":"48751628-917f-4969-8cb9-e01cd425fb82","type":"SendMessage","settings":{"id":"af1512bb-fde1-4710-b86a-9a4c5a1fd53c","type":"application/vnd.lime.chatstate+json","content":{"state":"composing","interval":1000}},"$cardContent":{"document":{"id":"af1512bb-fde1-4710-b86a-9a4c5a1fd53c","type":"application/vnd.lime.chatstate+json","content":{"state":"composing","interval":1000}},"editable":true,"deletable":true,"position":"left"}},"$invalid":false},{"action":{"$id":"56d23b7e-4daa-4463-94e3-ff89951eeb56","type":"SendMessage","settings":{"id":"a2a99f20-d164-40af-84c9-66c8fdb6a674","type":"application/vnd.lime.collection+json","content":{"itemType":"application/vnd.lime.document-select+json","items":[{"header":{"type":"application/vnd.lime.media-link+json","value":{"title":"{{cardOne@name}}","text":"{{cardOne@description}}","type":"image/jpeg","uri":"{{cardOne@avatar}}","aspectRatio":"2:1"}},"options":[],"id":0,"editing":false},{"header":{"type":"application/vnd.lime.media-link+json","value":{"title":"{{cardTwo@name}}","text":"{{cardTwo@description}}","type":"image/jpeg","uri":"{{cardTwo@avatar}}","aspectRatio":"2:1"}},"options":[],"id":1,"editing":false},{"header":{"type":"application/vnd.lime.media-link+json","value":{"title":"{{cardThree@name}}","text":"{{cardThree@description}}","type":"image/jpeg","uri":"{{cardThree@avatar}}","aspectRatio":"2:1"}},"options":[],"editing":false,"id":2},{"header":{"type":"application/vnd.lime.media-link+json","value":{"title":"{{cardFour@name}}","text":"{{cardFour@description}}","type":"image/jpeg","uri":"{{cardFour@avatar}}","aspectRatio":"2:1"}},"options":[],"editing":false,"id":3},{"header":{"type":"application/vnd.lime.media-link+json","value":{"title":"{{cardFive@name}}","text":"{{cardFive@description}}","type":"image/jpeg","uri":"{{cardFive@avatar}}","aspectRatio":"2:1"}},"options":[],"editing":false}]},"metadata":{}},"$cardContent":{"document":{"id":"a2a99f20-d164-40af-84c9-66c8fdb6a674","type":"application/vnd.lime.collection+json","content":{"itemType":"application/vnd.lime.document-select+json","items":[{"header":{"type":"application/vnd.lime.media-link+json","value":{"title":"{{cardOne@name}}","text":"{{cardOne@description}}","type":"image/jpeg","uri":"{{cardOne@avatar}}","aspectRatio":"2:1"}},"options":[],"id":0,"editing":false},{"header":{"type":"application/vnd.lime.media-link+json","value":{"title":"{{cardTwo@name}}","text":"{{cardTwo@description}}","type":"image/jpeg","uri":"{{cardTwo@avatar}}","aspectRatio":"2:1"}},"options":[],"id":1,"editing":false},{"header":{"type":"application/vnd.lime.media-link+json","value":{"title":"{{cardThree@name}}","text":"{{cardThree@description}}","type":"image/jpeg","uri":"{{cardThree@avatar}}","aspectRatio":"2:1"}},"options":[],"editing":false,"id":2},{"header":{"type":"application/vnd.lime.media-link+json","value":{"title":"{{cardFour@name}}","text":"{{cardFour@description}}","type":"image/jpeg","uri":"{{cardFour@avatar}}","aspectRatio":"2:1"}},"options":[],"editing":false,"id":3},{"header":{"type":"application/vnd.lime.media-link+json","value":{"title":"{{cardFive@name}}","text":"{{cardFive@description}}","type":"image/jpeg","uri":"{{cardFive@avatar}}","aspectRatio":"2:1"}},"options":[],"editing":false}]}},"editable":true,"deletable":true,"position":"left"}},"$invalid":false},{"input":{"bypass":true,"$cardContent":{"document":{"id":"068468d4-0e86-43d1-b165-1a44c569e38f","type":"text/plain","textContent":"Entrada do usuário","content":"Entrada do usuário"},"editable":false,"deletable":true,"position":"right","editing":false},"$invalid":false},"$invalid":false}],"$conditionOutputs":[{"stateId":"f6df1391-b0ed-423c-be6c-8ac2be25f321","$connId":"con_128","$id":"eef2130a-4625-488a-89d5-149c0a7b320a","conditions":[{"source":"input","comparison":"exists","values":[]}],"$invalid":false}],"$enteringCustomActions":[{"$id":"e1182202-3006-46d2-b19f-c84b8ac73a8e","type":"ProcessHttp","$title":"Requisição HTTP","$invalid":false,"settings":{"headers":{},"uri":"https://desafio-take-github.herokuapp.com/api/get-repos-take","method":"GET","responseStatusVariable":"status","responseBodyVariable":"resposta"},"conditions":[]},{"$id":"8631fb7d-27ef-4af0-8338-b0d8c2cb6b5d","type":"ExecuteScript","$title":"Executar script","$invalid":false,"settings":{"function":"run","source":"function run(resposta) {\n    var json = JSON.parse(resposta);\n    var cardOne = json.message[0]\n    return cardOne;\n}","inputVariables":["resposta"],"outputVariable":"cardOne","LocalTimeZoneEnabled":false},"conditions":[]},{"$id":"ed9fd3a2-e5ca-459b-88ee-0aee222480ba","type":"ExecuteScript","$title":"Executar script","$invalid":false,"settings":{"function":"run","source":"function run(resposta) {\n    var json = JSON.parse(resposta);\n    var cardTwo = json.message[1]\n    return cardTwo;\n}","inputVariables":["resposta"],"outputVariable":"cardTwo","LocalTimeZoneEnabled":false},"conditions":[]},{"$id":"37e930a2-286d-4fef-858a-876a96d6997b","type":"ExecuteScript","$title":"Executar script","$invalid":false,"settings":{"function":"run","source":"function run(resposta) {\n    var json = JSON.parse(resposta);\n    var cardThree = json.message[2]\n    return cardThree;\n}","inputVariables":["resposta"],"outputVariable":"cardThree","LocalTimeZoneEnabled":false},"conditions":[]},{"$id":"471f9d73-785d-4c06-a746-3072d6f9ac65","type":"ExecuteScript","$title":"Executar script","$invalid":false,"settings":{"function":"run","source":"function run(resposta) {\n    var json = JSON.parse(resposta);\n    var cardFour = json.message[3]\n    return cardFour;\n}","inputVariables":["resposta"],"outputVariable":"cardFour","LocalTimeZoneEnabled":false},"conditions":[]},{"$id":"38af89f5-dece-4f03-8392-2837f76fa71e","type":"ExecuteScript","$title":"Executar script","$invalid":false,"settings":{"function":"run","source":"function run(resposta) {\n    var json = JSON.parse(resposta);\n    var cardFive = json.message[4]\n    return cardFive;\n}","inputVariables":["resposta"],"outputVariable":"cardFive","LocalTimeZoneEnabled":false},"conditions":[]}],"$leavingCustomActions":[],"$inputSuggestions":["First option","Second option"],"$defaultOutput":{"stateId":"fallback","$invalid":false},"$tags":[],"id":"eb45fcef-9f9a-4395-ad28-b21494eea486","root":false,"$title":"Github Repositories","$position":{"top":"846px","left":"1915px"},"$invalidContentActions":false,"$invalidOutputs":false,"$invalidCustomActions":false,"$invalid":false}}